xor/xor.v
`timescale 1ns/1ns
module test;
    reg a,b;
    wire c;
    reg [1:0] x=2'b00;
    xor uut(c,a,b);
    initial begin
        $dumpfile("test.vcd");
        $dumpvars(0,test); 
        repeat (40) begin
            x=x+1;
            a=x[0];
            b=x[1];
            #50;
        end          
    end
endmodule

xor/test.vcd
$date
	Mon May 09 22:39:52 2022
$end
$version
	Icarus Verilog
$end
$timescale
	1ns
$end
$scope module test $end
$var wire 1 ! c $end
$var reg 1 " a $end
$var reg 1 # b $end
$var reg 2 $ x [1:0] $end
$upscope $end
$enddefinitions $end
#0
$dumpvars
b1 $
0#
1"
1!
$end
#50
1#
0"
b10 $
#100
0!
1"
b11 $
#150
0#
0"
b0 $
#200
1!
1"
b1 $
#250
1#
0"
b10 $
#300
0!
1"
b11 $
#350
0#
0"
b0 $
#400
1!
1"
b1 $
#450
1#
0"
b10 $
#500
0!
1"
b11 $
#550
0#
0"
b0 $
#600
1!
1"
b1 $
#650
1#
0"
b10 $
#700
0!
1"
b11 $
#750
0#
0"
b0 $
#800
1!
1"
b1 $
#850
1#
0"
b10 $
#900
0!
1"
b11 $
#950
0#
0"
b0 $
#1000
1!
1"
b1 $
#1050
1#
0"
b10 $
#1100
0!
1"
b11 $
#1150
0#
0"
b0 $
#1200
1!
1"
b1 $
#1250
1#
0"
b10 $
#1300
0!
1"
b11 $
#1350
0#
0"
b0 $
#1400
1!
1"
b1 $
#1450
1#
0"
b10 $
#1500
0!
1"
b11 $
#1550
0#
0"
b0 $
#1600
1!
1"
b1 $
#1650
1#
0"
b10 $
#1700
0!
1"
b11 $
#1750
0#
0"
b0 $
#1800
1!
1"
b1 $
#1850
1#
0"
b10 $
#1900
0!
1"
b11 $
#1950
0#
0"
b0 $
